pullout/__init__.py
pullout/core.py
pullout/types.py
pullout/utils.py
pullout-0.1.0.dist-info/METADATA
pullout-0.1.0.dist-info/WHEEL
pullout-0.1.0.dist-info/top_level.txt
pullout-0.1.0.dist-info/RECORD
