Metadata-Version: 2.4
Name: pullout
Version: 0.1.0
Summary: Easy way to pull out values from a complex nested Python structure
Author-email: Aleksei Trankov <trankov@yandex.ru>
Project-URL: Repository, https://gitverse.ru/trankov/pullout
Classifier: Programming Language :: Python :: 3
Classifier: License :: OSI Approved :: MIT License
Classifier: Operating System :: OS Independent
Requires-Python: >=3.12
